[  {
    "id": 1,
    "title": "Sterling",
    "price": 3199,
    "image": "/src/assets/NobleClosed.png",
    "imageHover": "/src/assets/NobleOpen.png"
  },
  {
    "id": 2,
    "title": "Sterling",
    "price": 3199,
    "image": "/src/assets/NobleClosed.png",
    "imageHover": "/src/assets/NobleOpen.png"
  },
  {
    "id": 3,
    "title": "Sterling",
    "price": 3199,
    "image": "/src/assets/NobleClosed.png",
    "imageHover": "/src/assets/NobleOpen.png"
  },
  {
    "id": 4,
    "title": "Sterling",
    "price": 3199,
    "image": "/src/assets/NobleClosed.png",
    "imageHover": "/src/assets/NobleOpen.png"
  },
  {
    "id": 5,
    "title": "Sterling",
    "price": 3199,
    "image": "/src/assets/NobleClosed.png",
    "imageHover": "/src/assets/NobleOpen.png"
  },
  {
    "id": 6,
    "title": "Sterling",
    "price": 3199,
    "image": "/src/assets/NobleClosed.png",
    "imageHover": "/src/assets/NobleOpen.png"
  },
  {
    "id": 7,
    "title": "Sterling",
    "price": 3199,
    "image": "/src/assets/NobleClosed.png",
    "imageHover": "/src/assets/NobleOpen.png"
  },
  {
    "id": 8,
    "title": "Sterling",
    "price": 3199,
    "image": "/src/assets/NobleClosed.png",
    "imageHover": "/src/assets/NobleOpen.png"
  },
  {
    "id": 9,
    "title": "Sterling",
    "price": 3199,
    "image": "/src/assets/NobleClosed.png",
    "imageHover": "/src/assets/NobleOpen.png"
  },
  {
    "id": 10,
    "title": "Sterling",
    "price": 3199,
    "image": "/src/assets/NobleClosed.png",
    "imageHover": "/src/assets/NobleOpen.png"
  },
    {
        "id": 11,
        "title": "Rock Lee",
        "price": 3199,
        "image": "/src/assets/RockLeePlain.png",
        "imageHover": "/src/assets/RockLee.png"
      },
      {
        "id": 12,
        "title": "Kakashi Obito",
        "price": 3199,
        "image": "/src/assets/KakashiObitoPlain.png",
        "imageHover": "/src/assets/KakashiObito.png"
      },
      {
        "id": 13,
        "title": "Itachi",
        "price": 3199,
        "image": "/src/assets/ItachiPlain.png",
        "imageHover": "/src/assets/Itachi.png"
      },
        {
          "id": 14,
          "title": "Sasuke Itachi",
          "price": 3199,
          "image": "/src/assets/SasukeItachiPlain.png",
          "imageHover": "/src/assets/SasukeItachi.png"
        },
        {
          "id": 15,
          "title": "Shisui",
          "price": 3499,
          "image": "/src/assets/ShisuiPlain.png",
          "imageHover": "/src/assets/Shisui.png"
        },
        {
          "id": 16,
          "title": "Rock Lee",
          "price": 3199,
          "image": "/src/assets/RockLeePlain.png",
          "imageHover": "/src/assets/RockLee.png"
        },
        {
          "id": 17,
          "title": "Kakashi Obito",
          "price": 3199,
          "image": "/src/assets/KakashiObitoPlain.png",
          "imageHover": "/src/assets/KakashiObito.png"
        },
        {
          "id": 18,
          "title": "Itachi",
          "price": 3199,
          "image": "/src/assets/ItachiPlain.png",
          "imageHover": "/src/assets/Itachi.png"
        },
          {
            "id": 19,
            "title": "Sasuke Itachi",
            "price": 3199,
            "image": "/src/assets/SasukeItachiPlain.png",
            "imageHover": "/src/assets/SasukeItachi.png"
          },
          {
            "id": 20,
            "title": "Shisui",
            "price": 3499,
            "image": "/src/assets/ShisuiPlain.png",
            "imageHover": "/src/assets/Shisui.png"
          },
    {
      "id": 21,
      "title": "Rock Lee",
      "price": 3199,
      "image": "/src/assets/RockLeePlain.png",
      "imageHover": "/src/assets/RockLee.png"
    },
    {
      "id": 22,
      "title": "Kakashi Obito",
      "price": 3199,
      "image": "/src/assets/KakashiObitoPlain.png",
      "imageHover": "/src/assets/KakashiObito.png"
    },
    {
      "id": 23,
      "title": "Itachi",
      "price": 3199,
      "image": "/src/assets/ItachiPlain.png",
      "imageHover": "/src/assets/Itachi.png"
    },
      {
        "id": 24,
        "title": "Sasuke Itachi",
        "price": 3199,
        "image": "/src/assets/SasukeItachiPlain.png",
        "imageHover": "/src/assets/SasukeItachi.png"
      },
      {
        "id": 25,
        "title": "Shisui",
        "price": 3499,
        "image": "/src/assets/ShisuiPlain.png",
        "imageHover": "/src/assets/Shisui.png"
      },
      {
        "id": 26,
        "title": "Rock Lee",
        "price": 3199,
        "image": "/src/assets/RockLeePlain.png",
        "imageHover": "/src/assets/RockLee.png"
      },
      {
        "id": 27,
        "title": "Kakashi Obito",
        "price": 3199,
        "image": "/src/assets/KakashiObitoPlain.png",
        "imageHover": "/src/assets/KakashiObito.png"
      },
      {
        "id": 28,
        "title": "Itachi",
        "price": 3199,
        "image": "/src/assets/ItachiPlain.png",
        "imageHover": "/src/assets/Itachi.png"
      },
        {
          "id": 29,
          "title": "Sasuke Itachi",
          "price": 3199,
          "image": "/src/assets/SasukeItachiPlain.png",
          "imageHover": "/src/assets/SasukeItachi.png"
        },
        {
          "id": 30,
          "title": "Shisui",
          "price": 3499,
          "image": "/src/assets/ShisuiPlain.png",
          "imageHover": "/src/assets/Shisui.png"
        }
        
    ]
    